divide/__init__.py
divide/divide_by_three.py
multiply/__init__.py
multiply/multiply_by_three.py
basicpkg_sardorbek-1.0.0.dist-info/LICENSE.txt
basicpkg_sardorbek-1.0.0.dist-info/METADATA
basicpkg_sardorbek-1.0.0.dist-info/WHEEL
basicpkg_sardorbek-1.0.0.dist-info/top_level.txt
basicpkg_sardorbek-1.0.0.dist-info/RECORD
