Metadata-Version: 2.1
Name: basicpkg-sardorbek
Version: 1.0.0
Summary: A simple Python package
Home-page: https://gitlab.com/codasteroid/basicpkg
Author: Sardorbek
Author-email: sardorbekqozoqov2281@gmail.com
Project-URL: Bug Tracker, https://gitlab.com/codasteroid/basicpkg/-/issues
Project-URL: repository, https://gitlab.com/codasteroid/basicpkg
Classifier: Programming Language :: Python :: 3
Classifier: License :: OSI Approved :: MIT License
Classifier: Operating System :: OS Independent
Requires-Python: >=3.6
License-File: LICENSE.txt
